pytest_anyio.py
pytest_anyio-0.0.0.dist-info/LICENSE
pytest_anyio-0.0.0.dist-info/WHEEL
pytest_anyio-0.0.0.dist-info/METADATA
pytest_anyio-0.0.0.dist-info/RECORD
